LICENSE
MANIFEST.in
README.rst
setup.cfg
setup.py
django_ecard.egg-info/PKG-INFO
django_ecard.egg-info/SOURCES.txt
django_ecard.egg-info/dependency_links.txt
django_ecard.egg-info/top_level.txt
ecard/__init__.py
ecard/admin.py
ecard/apps.py
ecard/colabRDP.py
ecard/forms.py
ecard/models.py
ecard/tests.py
ecard/urls.py
ecard/views.py
ecard/migrations/0001_initial.py
ecard/migrations/__init__.py
ecard/static/1.docx
ecard/static/2.docx
ecard/static/BNAZANIN.TTF
ecard/static/BTITR.TTF
ecard/static/favicon.ico
ecard/static/jquery-1.10.1.min.js
ecard/static/logo.png
ecard/static/main.css
ecard/static/persianDatepicker-default.css
ecard/static/persianDatepicker.js
ecard/static/spinners.css
ecard/static/bt/css/bootstrap.min.css
ecard/static/bt/css/font-awesome.min.css
ecard/static/bt/css/style.css
ecard/static/bt/fonts/BNAZANIN.TTF
ecard/static/bt/fonts/BTITR.TTF
ecard/static/bt/fonts/FontAwesome.otf
ecard/static/bt/fonts/Vazir-FD.eot
ecard/static/bt/fonts/Vazir-FD.ttf
ecard/static/bt/fonts/Vazir-FD.woff
ecard/static/bt/fonts/Vazir-FD.woff2
ecard/static/bt/fonts/fontawesome-webfont.eot
ecard/static/bt/fonts/fontawesome-webfont.svg
ecard/static/bt/fonts/fontawesome-webfont.ttf
ecard/static/bt/fonts/fontawesome-webfont.woff
ecard/static/bt/fonts/fontawesome-webfont.woff2
ecard/static/bt/js/creative.js
ecard/static/bt/js/creative.min.js
ecard/static/bt/pics/bg-masthead.jpg
ecard/static/bt/pics/portfolio/fullsize/1.jpg
ecard/static/bt/pics/portfolio/fullsize/2.jpg
ecard/static/bt/pics/portfolio/fullsize/3.jpg
ecard/static/bt/pics/portfolio/fullsize/4.jpg
ecard/static/bt/pics/portfolio/fullsize/5.jpg
ecard/static/bt/pics/portfolio/fullsize/6.jpg
ecard/static/bt/pics/portfolio/thumbnails/1.jpg
ecard/static/bt/pics/portfolio/thumbnails/2.jpg
ecard/static/bt/pics/portfolio/thumbnails/3.jpg
ecard/static/bt/pics/portfolio/thumbnails/4.jpg
ecard/static/bt/pics/portfolio/thumbnails/5.jpg
ecard/static/bt/pics/portfolio/thumbnails/6.jpg
ecard/static/bt/vendor/bootstrap/js/bootstrap.bundle.js
ecard/static/bt/vendor/bootstrap/js/bootstrap.bundle.js.map
ecard/static/bt/vendor/bootstrap/js/bootstrap.bundle.min.js
