Metadata-Version: 2.1
Name: django-ecard
Version: 1.0
Summary: A Django app to craete card.
Home-page: https://www.epg.eu.pythonanywhere.com/
Author: epg
Author-email: epg900@gmail.com
License: GNU GENERAL PUBLIC LICENSE
Platform: UNKNOWN
Requires-Python: >=3.8
License-File: LICENSE
